lbgpt/__init__.py
lbgpt/allocation.py
lbgpt/base.py
lbgpt/cache.py
lbgpt/lbgpt.py
lbgpt/types.py
lbgpt/usage.py
lbgpt/utils.py
lbgpt/caches/__init__.py
lbgpt/caches/s3.py
lbgpt/semantic_cache/__init__.py
lbgpt/semantic_cache/base.py
lbgpt/semantic_cache/encoding.py
lbgpt/semantic_cache/faiss_cache.py
lbgpt/semantic_cache/qdrant_cache.py
lbgpt-0.7.1.dist-info/METADATA
lbgpt-0.7.1.dist-info/WHEEL
lbgpt-0.7.1.dist-info/licenses/LICENSE
lbgpt-0.7.1.dist-info/RECORD
